[
    {
        "time": "Sun, 25 May 2025 15:22:20 +0300",
        "title": "Zirai don destek ödemelerinde detaylar açıklandı",
        "content": "Zirai Don Meclis Araştırma Komisyonu Başkan Vekili AK Parti Malatya Milletvekili Bülent Tüfenkci, zirai don destek ödemelerine ilişkin bilgi vererek, Kurban Bayramı&#039;ndan sonra gerçekleşeceğini aktardı.",
        "link": "https://www.ensonhaber.com/ekonomi/zirai-don-destek-odemelerinde-detaylar-aciklandi",
        "img": "https://icdn.ensonhaber.com/crop/1200x675/resimler/diger/kok/2025/05/25/6832fe29dbf77645.jpg"
    },
    {
        "time": "Sun, 25 May 2025 15:19:00 +0300",
        "title": "Cumhurbaşkanı Erdoğan, 'Her Mahallesiyle İstanbul' programında",
        "content": "Cumhurbaşkanı Erdoğan, İstanbul Kongre Merkezi&#039;nde düzenlenen, &#039;Her Mahallesiyle İstanbul&#039; programına katıldı. Burada konuşma gerçekleştiren Erdoğan, önemli açıklamalarda bulunuyor.",
        "link": "https://www.ensonhaber.com/gundem/cumhurbaskani-erdogan-her-mahallesiyle-istanbul-programinda",
        "img": "https://icdn.ensonhaber.com/crop/1200x675/resimler/diger/kok/2025/05/25/6833079375019589.jpg"
    },
    {
        "time": "Sun, 25 May 2025 15:16:48 +0300",
        "title": "Türkiye, 2025'in en yeşil rotaları arasında yer aldı",
        "content": "Türkiye, milyonlarca okuyucuya ulaşan seyahat dergisi Wanderlust&#039;ın &quot;Travel Green List&quot; seçkisinde 2025&#039;in en yeşil rotaları arasında yer aldı.",
        "link": "https://www.ensonhaber.com/ekonomi/turkiye-2025in-en-yesil-rotalari-arasinda-yer-aldi",
        "img": "https://icdn.ensonhaber.com/crop/1200x675/resimler/diger/kok/2025/05/25/683306c5988e6155.jpg"
    },
    {
        "time": "Sun, 25 May 2025 15:07:25 +0300",
        "title": "Kronikleşmiş kadastro davaları çözüme kavuşuyor",
        "content": "Adalet Bakanı Yılmaz Tunç, Sıfır Kadastro Dosyası Projesi kapsamında, yılın ilk 3 ayında 7 bin 94 kararın verildiğini, bu kararlarda toplam 75 bin 726 taraf ve 20 bin 270 parsel hakkında hüküm tesis edildiğini açıkladı.",
        "link": "https://www.ensonhaber.com/gundem/kroniklesmis-kadastro-davalari-cozume-kavusuyor",
        "img": "https://icdn.ensonhaber.com/crop/1200x675/resimler/diger/kok/2025/05/25/683307e991335264.jpg"
    },
    {
        "time": "Sun, 25 May 2025 15:07:23 +0300",
        "title": "Balıkesir'de erkek arkadaşının katlettiği Dilruba'ya veda",
        "content": "Erkek arkadaşı Burak İnci tarafından bıçaklanarak öldürülen Dilruba Elif Çetin’in cenazesi, Antalya’da annesinin yanına defnedildi",
        "link": "https://www.ensonhaber.com/3-sayfa/balikesirde-erkek-arkadasinin-katlettigi-dilrubaya-veda",
        "img": "https://icdn.ensonhaber.com/crop/1200x675/resimler/diger/kok/2025/05/25/68330710a5185103.jpg"
    },
    {
        "time": "Sun, 25 May 2025 15:06:58 +0300",
        "title": "Erzurum'da toprak kayması meydana geldi",
        "content": "Uzundere ilçesinde meydana gelen toprak kayması sonucu bazı yollarda, tarım arazilerinde ve evlerde hasar oluştu. İhbar üzerine bölgeye Devlet Su İşleri (DSİ), Tarım ve Hayvancılık İl Müdürlüğü, kolluk kuvvetleri ile AFAD ekipleri sevk edildi.",
        "link": "https://www.ensonhaber.com/3-sayfa/erzurumun-toprak-kaymasi-meydana-geldi",
        "img": "https://icdn.ensonhaber.com/crop/1200x675/resimler/diger/kok/2025/05/25/683305e4a4e25796.jpg"
    },
    {
        "time": "Sun, 25 May 2025 15:01:05 +0300",
        "title": "DEM Parti siyasi turunda: Yeni durak MHP",
        "content": "Terörsüz Türkiye süreci kapsamında siyasi parti turlarını sürdüren DEM Parti, MHP&#039;yi 27 Mayıs Salı günü saat 11.30&#039;da TBMM&#039;de ziyaret edecek.",
        "link": "https://www.ensonhaber.com/gundem/dem-parti-siyasi-turunda-yeni-durak-mhp",
        "img": "https://icdn.ensonhaber.com/crop/1200x675/resimler/diger/kok/2025/05/25/6833062f663d3244.jpg"
    },
    {
        "time": "Sun, 25 May 2025 14:58:09 +0300",
        "title": "Cihan Çanak'ın adalesinde yaralanma tespit edildi",
        "content": "Trabzonsporlu futbolcu Cihan Çanak&#039;ın sol arka üst adalesinde yaralanma tespit edildi.",
        "link": "https://www.ensonhaber.com/kralspor/futbol/cihan-canakin-adalesinde-yaralanma-tespit-edildi",
        "img": "https://icdn.ensonhaber.com/crop/1200x675/resimler/diger/kok/2025/05/25/683305bbaf2f2160.jpg"
    },
    {
        "time": "Sun, 25 May 2025 14:56:24 +0300",
        "title": "Gazze'de can kaybı 53 bin 939'a yükseldi",
        "content": "Filistin Sağlık Bakanlığı&#039;ndan yapılan açıklamada, İsrail&#039;in Gazze&#039;ye saldırılarında can kaybı 53 bin 939&#039;a yükseldiği ve son 24 saatte hastanelere 204 yararlının getirildiği bildirildi.",
        "link": "https://www.ensonhaber.com/dunya/gazzede-can-kaybi-53-bin-939a-yukseldi",
        "img": "https://icdn.ensonhaber.com/crop/1200x675/resimler/diger/kok/2025/05/25/6833054d22ff6868.jpg"
    },
    {
        "time": "Sun, 25 May 2025 14:56:17 +0300",
        "title": "Ümit Yenişehirli yazdı: Her türlü zorluğu çıkarmışlardı",
        "content": "Ümit Yenişehirli, CHP’nin tek parti iktidarı döneminde Türk vatandaşlarının hacca gitmesiyle ilgili uygulamaları kaleme aldı.",
        "link": "https://www.ensonhaber.com/tarih-haberleri/umit-yenisehirli-yazdi-her-turlu-zorlugu-cikarmislardi",
        "img": "https://icdn.ensonhaber.com/crop/1200x675/resimler/diger/kok/2025/05/25/6833061c24337809.jpg"
    },
    {
        "time": "Sun, 25 May 2025 14:49:59 +0300",
        "title": "Batman'da kamyonet dereye uçtu: 1 ölü",
        "content": "Sason ilçesinde dereye yuvarlanan kamyonetin sürücüsü hayatını kaybederken, olay yerine jandarma ve sağlık ekipleri sevk edildi.",
        "link": "https://www.ensonhaber.com/3-sayfa/batmanda-kamyonet-dereye-uctu-1-olu",
        "img": "https://icdn.ensonhaber.com/crop/1200x675/resimler/diger/kok/2025/05/25/68330485e0f80783.jpg"
    },
    {
        "time": "Sun, 25 May 2025 14:49:15 +0300",
        "title": "Yozgat'ta feci kaza: 6 yaralı",
        "content": "Yerköy ilçesinde otomobil ile cipin çarpıştığı kazada 1&#039;i ağır 6 kişi yaralandı.",
        "link": "https://www.ensonhaber.com/3-sayfa/yozgatta-feci-kaza-6-yarali",
        "img": "https://icdn.ensonhaber.com/crop/1200x675/resimler/diger/kok/2025/05/25/683303b3c8106490.jpg"
    },
    {
        "time": "Sun, 25 May 2025 14:45:16 +0300",
        "title": "Çay içmenin faydaları nelerdir? İşte çay içmenin 6 faydası",
        "content": "Ülkemizde en çok tüketilen içecekler arasında yer alan çayın faydalarını sizler için derledik. İşte çay içmenin faydaları...",
        "link": "https://www.ensonhaber.com/bilgi/cay-icmenin-faydalari-nelerdir-iste-cay-icmenin-6-faydasi",
        "img": "https://icdn.ensonhaber.com/crop/1200x675/resimler/diger/kok/2025/05/25/6832438e8b267127.jpg"
    },
    {
        "time": "Sun, 25 May 2025 14:38:24 +0300",
        "title": "Trabzon'da odun kırarak ayda 80 bin TL kazanıyor",
        "content": "Araklı ilçesinde yaşayan 49 yaşındaki Paşa Yıldız, küçük yaşlardan beri yaptığı odun kırma işiyle gençlere taş çıkartıyor. Günde 3 ton odun kıran Yıldız, fırınlara çalışarak ayda 80 bin TL gelir elde ediyor.",
        "link": "https://www.ensonhaber.com/yasam/trabzonda-odun-kirarak-ayda-80-bin-tl-kazaniyor",
        "img": "https://icdn.ensonhaber.com/crop/1200x675/resimler/diger/kok/2025/05/25/6833010eead11776.jpg"
    },
    {
        "time": "Sun, 25 May 2025 14:37:26 +0300",
        "title": "İran'dan doğu sınırına 400 kilometre güvenlik duvarı",
        "content": "İran Kara Kuvvetleri Komutanı Haydari, Afganistan ve Pakistan&#039;ın yer aldığı doğu sınırına 400 kilometre güvenlik duvarı inşa edileceğini açıkladı.",
        "link": "https://www.ensonhaber.com/dunya/irandan-dogu-sinirina-400-kilometre-guvenlik-duvari",
        "img": "https://icdn.ensonhaber.com/crop/1200x675/resimler/diger/kok/2025/05/25/6832ff27ba2e8867.jpg"
    },
    {
        "time": "Sun, 25 May 2025 14:37:19 +0300",
        "title": "Cumhurbaşkanı Erdoğan'dan Necip Fazıl Kısakürek paylaşımı",
        "content": "Cumhurbaşkanı Recep Tayyip Erdoğan, sosyal medya hesabında yaptığı bir paylaşımla, vefatının 42&#039;nci yılında Necip Fazıl Kısakürek&#039;i rahmetle yad etti.",
        "link": "https://www.ensonhaber.com/gundem/cumhurbaskani-erdogandan-necip-fazil-kisakurek-paylasimi-32383",
        "img": "https://icdn.ensonhaber.com/crop/1200x675/resimler/diger/kok/2025/05/25/6832fdc2378bc292.jpg"
    },
    {
        "time": "Sun, 25 May 2025 14:32:09 +0300",
        "title": "Gabar’dan sonra sıra Beytüşşebap'ta: Petrol aranıyor",
        "content": "Şırnak Gabar Dağı’nda bulunan petrolün ardından Beytüşşebap ilçesinde de petrol arama çalışmaları başladı.",
        "link": "https://www.ensonhaber.com/gundem/gabardan-sonra-beytuslebapta-da-petrol-araniyor",
        "img": "https://icdn.ensonhaber.com/crop/1200x675/resimler/diger/kok/2025/05/25/6832ff0888b43890.jpg"
    },
    {
        "time": "Sun, 25 May 2025 14:30:35 +0300",
        "title": "Tayland’da tanker kazası: 600 litre benzin yola döküldü",
        "content": "Bangkok’ta dün gece saatlerinde konteyner yüklü bir tır ile akaryakıt tankerinin çarpışması sonucu meydana gelen kazada, yaklaşık 600 litre benzin yola döküldü. Kaza anı kameraya yansıdı.",
        "link": "https://www.ensonhaber.com/3-sayfa/taylandda-tanker-kazasi-600-litre-benzin-yola-dokuldu",
        "img": "https://icdn.ensonhaber.com/crop/1200x675/resimler/diger/kok/2025/05/25/6832ff4405a96168.jpg"
    },
    {
        "time": "Sun, 25 May 2025 14:29:11 +0300",
        "title": "İzmir'de 3 yaşındaki çocuk, tek başına bindiği motosikletten düştü",
        "content": "Menemen ilçesinde emlakçılık yapan babasının iş yerinde bulunan 3 yaşındaki Ömer Halis, esnaf komşunun motoruna binip çalıştırdı. Küçük çocuk, yürüttüğü motosikletle beraber devrilirken tehlikeli anlar kameraya yansıdı.",
        "link": "https://www.ensonhaber.com/3-sayfa/izmirde-3-yasindaki-cocuk-tek-basina-bindigi-motosikletten-dustu",
        "img": "https://icdn.ensonhaber.com/crop/1200x675/resimler/diger/kok/2025/05/25/6832fe93eb125667.jpg"
    },
    {
        "time": "Sun, 25 May 2025 14:28:07 +0300",
        "title": "Muğla'da çamur banyosu turistlerin ilgisini çekiyor",
        "content": "Muğla&#039;nın Ortaca ilçesinin dünyaca ünlü turistlik mahallesi Dalyan&#039;da çamur banyosu turistlerden ilgi görüyor.",
        "link": "https://www.ensonhaber.com/yasam/muglada-camur-banyosu-turistlerin-ilgisini-cekiyor",
        "img": "https://icdn.ensonhaber.com/crop/1200x675/resimler/diger/kok/2025/05/25/6832fe05ba2dc667.jpg"
    },
    {
        "time": "Sun, 25 May 2025 14:27:55 +0300",
        "title": "Deniz Öncü, İngiltere'de 19. oldu",
        "content": "Milli motosikletçi Deniz Öncü, Moto2 Dünya Şampiyonası&#039;nın İngiltere&#039;de düzenlenen 7. ayağında yarışı 19. sırada tamamladı.",
        "link": "https://www.ensonhaber.com/kralspor/motor-sporlari/deniz-oncu-ingilterede-19-oldu",
        "img": "https://icdn.ensonhaber.com/crop/1200x675/resimler/diger/kok/2025/05/25/6832fe67d8493900.jpg"
    },
    {
        "time": "Sun, 25 May 2025 14:21:52 +0300",
        "title": "Rusya ve Ukrayna esir takasını tamamladı",
        "content": "Rusya ve Ukrayna arasında 3 günlük savaş esiri takası tamamlandı. İki ülke arasında toplamda biner kişilik esir takası yapıldı.",
        "link": "https://www.ensonhaber.com/dunya/rusya-ve-ukrayna-esir-takasini-tamamladi",
        "img": "https://icdn.ensonhaber.com/crop/1200x675/resimler/diger/kok/2025/05/25/6832f9c1ee365718.jpg"
    },
    {
        "time": "Sun, 25 May 2025 14:16:45 +0300",
        "title": "Nergis Kumbasar ve Mehmet Ali Erbil arasında nafaka sürtüşmesi",
        "content": "Ünlü oyuncu Nergis Kumbasar, Mehmet Ali Erbil’in nafaka açıklamasına üstü kapalı şekilde göz dağı verdi. &quot;Eğer istersem çok canı acır&quot; diye konuştu.",
        "link": "https://www.ensonhaber.com/magazin/nergis-kumbasar-ve-mehmet-ali-erbil-arasinda-nafaka-surtusmesi",
        "img": "https://icdn.ensonhaber.com/crop/1200x675/resimler/diger/kok/2025/05/25/6832fa91e46e0337.jpg"
    },
    {
        "time": "Sun, 25 May 2025 14:14:46 +0300",
        "title": "Osmaniye'de bahçeye giren yılanla hatıra fotoğrafı çektirdiler",
        "content": "Kent merkezinde bahçeye giren bir buçuk metrelik kara yılanı yakalayan itfaiyeci yılana su içirirken, bazı vatandaşların yılanla hatıra fotoğrafı çektirdiği anlar da kameralara yansıdı.",
        "link": "https://www.ensonhaber.com/yasam/osmaniyede-bahceye-giren-yilanla-hatira-fotografi-cektirdiler",
        "img": "https://icdn.ensonhaber.com/crop/1200x675/resimler/diger/kok/2025/05/25/6832fb3bdae0f953.jpg"
    },
    {
        "time": "Sun, 25 May 2025 14:13:51 +0300",
        "title": "Fethiye’de dalgıçlardan su altında şampiyonluk kutlaması!",
        "content": "Fethiye’de bir grup dalgıç, su altında sarı-kırmızılı bayraklarla resmi geçit yaparak Galatasaray&#039;ın şampiyonluğunu kutladı.",
        "link": "https://www.ensonhaber.com/kralspor/futbol/fethiyede-dalgiclardan-su-altinda-sampiyonluk-kutlamasi",
        "img": "https://icdn.ensonhaber.com/crop/1200x675/resimler/diger/kok/2025/05/25/6832f75a4c395619.jpg"
    }
]